common/__init__.py
common/bdinfo_string.py
common/bittorrent.py
common/command.py
common/constants.py
common/database.py
common/extractor.py
common/frames.py
common/mediainfo.py
common/mediainfo_string.py
common/settings.py
common/title.py
common/torrent_clients.py
common/utility.py
common/external_services/__init__.py
common/external_services/imageHost.py
common/external_services/imdb.py
common/external_services/mediaresult.py
common/external_services/ftpx/__init__.py
common/external_services/ftpx/client.py
common/external_services/ftpx/core/__init__.py
common/external_services/ftpx/core/ftpx_service.py
common/external_services/ftpx/core/ftpx_session.py
common/external_services/ftpx/core/menu.py
common/external_services/ftpx/core/models/__init__.py
common/external_services/ftpx/core/models/list.py
common/external_services/igdb/__init__.py
common/external_services/igdb/client.py
common/external_services/igdb/core/__init__.py
common/external_services/igdb/core/api.py
common/external_services/igdb/core/platformid.py
common/external_services/igdb/core/tags.py
common/external_services/igdb/core/models/__init__.py
common/external_services/igdb/core/models/search.py
common/external_services/sessions/__init__.py
common/external_services/sessions/agents.py
common/external_services/sessions/exceptions.py
common/external_services/sessions/session.py
common/external_services/theMovieDB/__init__.py
common/external_services/theMovieDB/core/__init__.py
common/external_services/theMovieDB/core/api.py
common/external_services/theMovieDB/core/keywords.py
common/external_services/theMovieDB/core/videos.py
common/external_services/theMovieDB/core/models/__init__.py
common/external_services/theMovieDB/core/models/movie/__init__.py
common/external_services/theMovieDB/core/models/movie/alternative_titles.py
common/external_services/theMovieDB/core/models/movie/details.py
common/external_services/theMovieDB/core/models/movie/movie.py
unit3dup-0.8.21.dist-info/licenses/LICENSE
unit3dup-0.8.21.dist-info/METADATA
unit3dup-0.8.21.dist-info/WHEEL
unit3dup-0.8.21.dist-info/entry_points.txt
unit3dup-0.8.21.dist-info/top_level.txt
unit3dup-0.8.21.dist-info/RECORD
