Metadata-Version: 2.4
Name: Unit3Dup
Version: 0.8.21
Summary: An uploader for the Unit3D torrent tracker
Author: Parzival
License-Expression: MIT
Project-URL: Homepage, https://github.com/31December99/Unit3Dup
Requires-Python: >=3.10
License-File: LICENSE
Requires-Dist: guessit==3.8.0
Requires-Dist: pymediainfo==6.1.0
Requires-Dist: python-qbittorrent==0.4.3
Requires-Dist: pydantic==2.10.6
Requires-Dist: requests==2.32.3
Requires-Dist: rich==13.7.1
Requires-Dist: torf==4.2.7
Requires-Dist: tqdm==4.66.5
Requires-Dist: thefuzz==0.22.1
Requires-Dist: unidecode==1.3.8
Requires-Dist: pillow==10.4.0
Requires-Dist: patool==2.4.0
Requires-Dist: diskcache==5.6.3
Requires-Dist: httpx==0.27.2
Requires-Dist: transmission-rpc==7.0.11
Requires-Dist: cinemagoer==2023.5.1
Requires-Dist: pathvalidate==3.2.3
Requires-Dist: bencode2==0.3.24
Requires-Dist: rtorrent-rpc==0.9.4
Dynamic: license-file
